triangulumancer.cpython-313-aarch64-linux-gnu.so
triangulumancer.libs/libcdd-9b904d71.so.0.0.0
triangulumancer.libs/libcddgmp-0c7893a5.so.0.0.0
triangulumancer.libs/libgmp-b1125f0a.so.10.5.0
triangulumancer.libs/libgmpxx-aa4c742b.so.4.7.0
triangulumancer.libs/libqsopt_ex-c50615f3.so.2.1.0
triangulumancer-0.1.2.dist-info/METADATA
triangulumancer-0.1.2.dist-info/WHEEL
triangulumancer-0.1.2.dist-info/RECORD
triangulumancer-0.1.2.dist-info/licenses/LICENSE
